agsekit-1.0.2.data/data/share/agsekit/config-example.yaml
agsekit-1.0.2.dist-info/licenses/LICENSE
agsekit_cli/__init__.py
agsekit_cli/agents.py
agsekit_cli/backup.py
agsekit_cli/cli.py
agsekit_cli/config.py
agsekit_cli/i18n.py
agsekit_cli/interactive.py
agsekit_cli/mounts.py
agsekit_cli/run_with_proxychains.sh
agsekit_cli/vm.py
agsekit_cli/vm_bundle_definitions.py
agsekit_cli/vm_bundles.py
agsekit_cli/vm_prepare.py
agsekit_cli/agent_scripts/claude-code.sh
agsekit_cli/agent_scripts/codex-glibc.sh
agsekit_cli/agent_scripts/codex.sh
agsekit_cli/agent_scripts/proxychains_common.sh
agsekit_cli/agent_scripts/qwen.sh
agsekit_cli/commands/__init__.py
agsekit_cli/commands/addmount.py
agsekit_cli/commands/backup_clean.py
agsekit_cli/commands/backup_once.py
agsekit_cli/commands/backup_repeated.py
agsekit_cli/commands/config_example.py
agsekit_cli/commands/config_gen.py
agsekit_cli/commands/create_vm.py
agsekit_cli/commands/destroy_vm.py
agsekit_cli/commands/install_agents.py
agsekit_cli/commands/list_bundles.py
agsekit_cli/commands/mounts.py
agsekit_cli/commands/pip_upgrade.py
agsekit_cli/commands/portforward.py
agsekit_cli/commands/prepare.py
agsekit_cli/commands/removemount.py
agsekit_cli/commands/run.py
agsekit_cli/commands/shell.py
agsekit_cli/commands/ssh.py
agsekit_cli/commands/start_vm.py
agsekit_cli/commands/stop.py
agsekit_cli/commands/systemd.py
agsekit_cli/commands/version.py
agsekit_cli/locales/en.json
agsekit_cli/locales/ru.json
agsekit_cli/vm_installers/docker.sh
agsekit_cli/vm_installers/golang.sh
agsekit_cli/vm_installers/nodejs.sh
agsekit_cli/vm_installers/nvm.sh
agsekit_cli/vm_installers/pyenv.sh
agsekit_cli/vm_installers/python.sh
agsekit_cli/vm_installers/rust.sh
agsekit-1.0.2.dist-info/METADATA
agsekit-1.0.2.dist-info/WHEEL
agsekit-1.0.2.dist-info/entry_points.txt
agsekit-1.0.2.dist-info/top_level.txt
agsekit-1.0.2.dist-info/RECORD
