Metadata-Version: 2.4
Name: agsekit
Version: 1.0.2
Summary: Agent Safety Kit command-line utilities
Author-email: Mihanentalpo <mihanentalpo@yandex.ru>
License: MIT License
Requires-Python: >=3.9
License-File: LICENSE
Requires-Dist: click<9,>=8.1
Requires-Dist: PyYAML<7,>=6.0
Requires-Dist: questionary<3,>=2.0
Requires-Dist: ruamel.yaml<0.19,>=0.18
Requires-Dist: tomli>=2.0.1; python_version < "3.11"
Dynamic: license-file
